heqms_pkg/__init__.py
heqms_pkg/config.py
heqms_pkg/main.py
heqms_pkg/module.py
heqms_pkg/machine_learning/__init__.py
heqms_pkg/machine_learning/ml_pvdm.py
heqms_pkg/preprocess/__init__.py
heqms_pkg/preprocess/preprocessing.py
heqms_pkg/rel_db/__init__.py
heqms_pkg/rel_db/from_db.py
heqms_pkg/rel_db/save_result.py
heqms_pkg/rel_db/to_db.py
heqmsPkg-0.0.15.dist-info/METADATA
heqmsPkg-0.0.15.dist-info/WHEEL
heqmsPkg-0.0.15.dist-info/top_level.txt
heqmsPkg-0.0.15.dist-info/RECORD
