Metadata-Version: 2.1
Name: heqmsPkg
Version: 0.0.15
Summary: test package
Home-page: https://github.com/yiy829/Project1
Author: WAF
Author-email: iyyeo@repia.com
License: UNKNOWN
Platform: UNKNOWN
Classifier: Programming Language :: Python :: 3
Classifier: License :: OSI Approved :: MIT License
Classifier: Operating System :: OS Independent
Requires-Python: >=3.8
Requires-Dist: bleach (==3.2.1)
Requires-Dist: certifi (==2020.12.5)
Requires-Dist: cffi (==1.14.4)
Requires-Dist: chardet (==4.0.0)
Requires-Dist: click (==7.1.2)
Requires-Dist: colorama (==0.4.4)
Requires-Dist: cryptography (==3.3.1)
Requires-Dist: Cython (==0.29.14)
Requires-Dist: docutils (==0.16)
Requires-Dist: gensim (==3.8.3)
Requires-Dist: idna (==2.10)
Requires-Dist: joblib (==1.0.0)
Requires-Dist: keyring (==21.8.0)
Requires-Dist: mysqlclient (==2.0.3)
Requires-Dist: nltk (==3.5)
Requires-Dist: numpy (==1.19.2)
Requires-Dist: packaging (==20.8)
Requires-Dist: pandas (==1.2.0)
Requires-Dist: pkginfo (==1.6.1)
Requires-Dist: pycparser (==2.20)
Requires-Dist: Pygments (==2.7.3)
Requires-Dist: PyMySQL (==1.0.1)
Requires-Dist: pyparsing (==2.4.7)
Requires-Dist: pytz (==2020.5)
Requires-Dist: regex (==2020.11.13)
Requires-Dist: requests (==2.25.1)
Requires-Dist: rfc3986 (==1.4.0)
Requires-Dist: scipy (==1.6.0)
Requires-Dist: six (==1.15.0)
Requires-Dist: SQLAlchemy (==1.3.21)
Requires-Dist: tqdm (==4.55.1)
Requires-Dist: urllib3 (==1.26.2)
Requires-Dist: webencodings (==0.5.1)
Requires-Dist: wincertstore (==0.2)
